{"orderid":194241,"product":"USB-C Charging Cable","quantity":1,"price":11.95,"orderdate":"2019-05-16T13:55:00.000-05:00","storeaddress":"104 South St, New York City, NY 10001","city":" New York City","state":"NY"}
{"orderid":194357,"product":"USB-C Charging Cable","quantity":1,"price":11.95,"orderdate":"2019-05-08T10:24:00.000-05:00","storeaddress":"601 West St, San Francisco, CA 94016","city":" San Francisco","state":"CA"}
{"orderid":194673,"product":"LG Washing Machine","quantity":1,"price":600.0,"orderdate":"2019-05-12T12:50:00.000-05:00","storeaddress":"963 Maple St, Seattle, WA 98101","city":" Seattle","state":"WA"}
{"orderid":195086,"product":"Wired Headphones","quantity":1,"price":11.99,"orderdate":"2019-05-07T16:11:00.000-05:00","storeaddress":"5 Spruce St, Seattle, WA 98101","city":" Seattle","state":"WA"}
{"orderid":195175,"product":"Bose SoundSport Headphones","quantity":1,"price":99.99,"orderdate":"2019-05-14T17:06:00.000-05:00","storeaddress":"633 1st St, Los Angeles, CA 90001","city":" Los Angeles","state":"CA"}
{"orderid":195600,"product":"USB-C Charging Cable","quantity":1,"price":11.95,"orderdate":"2019-05-28T19:18:00.000-05:00","storeaddress":"26 Sunset St, Boston, MA 02215","city":" Boston","state":"MA"}
{"orderid":195719,"product":"Lightning Charging Cable","quantity":1,"price":14.95,"orderdate":"2019-05-11T07:53:00.000-05:00","storeaddress":"241 Park St, Boston, MA 02215","city":" Boston","state":"MA"}
{"orderid":195814,"product":"AAA Batteries (4-pack)","quantity":1,"price":2.99,"orderdate":"2019-05-10T00:27:00.000-05:00","storeaddress":"466 Jefferson St, San Francisco, CA 94016","city":" San Francisco","state":"CA"}
{"orderid":196077,"product":"Lightning Charging Cable","quantity":1,"price":14.95,"orderdate":"2019-05-26T10:15:00.000-05:00","storeaddress":"808 Jefferson St, Los Angeles, CA 90001","city":" Los Angeles","state":"CA"}
{"orderid":196128,"product":"Google Phone","quantity":1,"price":600.0,"orderdate":"2019-05-06T18:37:00.000-05:00","storeaddress":"848 2nd St, San Francisco, CA 94016","city":" San Francisco","state":"CA"}
{"orderid":196355,"product":"20in Monitor","quantity":1,"price":109.99,"orderdate":"2019-05-29T20:31:00.000-05:00","storeaddress":"719 Adams St, Atlanta, GA 30301","city":" Atlanta","state":"GA"}
{"orderid":196439,"product":"AA Batteries (4-pack)","quantity":1,"price":3.84,"orderdate":"2019-05-28T10:59:00.000-05:00","storeaddress":"572 14th St, San Francisco, CA 94016","city":" San Francisco","state":"CA"}
{"orderid":196844,"product":"Wired Headphones","quantity":1,"price":11.99,"orderdate":"2019-05-30T20:22:00.000-05:00","storeaddress":"959 8th St, Los Angeles, CA 90001","city":" Los Angeles","state":"CA"}
{"orderid":197171,"product":"Wired Headphones","quantity":1,"price":11.99,"orderdate":"2019-05-11T20:56:00.000-05:00","storeaddress":"370 Elm St, Dallas, TX 75001","city":" Dallas","state":"TX"}
{"orderid":197208,"product":"Wired Headphones","quantity":1,"price":11.99,"orderdate":"2019-05-18T12:41:00.000-05:00","storeaddress":"416 11th St, Portland, OR 97035","city":" Portland","state":"OR"}
{"orderid":197373,"product":"Apple Airpods Headphones","quantity":1,"price":150.0,"orderdate":"2019-05-24T21:05:00.000-05:00","storeaddress":"473 Sunset St, San Francisco, CA 94016","city":" San Francisco","state":"CA"}
{"orderid":197796,"product":"Flatscreen TV","quantity":1,"price":300.0,"orderdate":"2019-05-21T21:00:00.000-05:00","storeaddress":"254 Chestnut St, Los Angeles, CA 90001","city":" Los Angeles","state":"CA"}
{"orderid":198766,"product":"27in FHD Monitor","quantity":1,"price":149.99,"orderdate":"2019-05-23T19:40:00.000-05:00","storeaddress":"799 Park St, Boston, MA 02215","city":" Boston","state":"MA"}
{"orderid":198767,"product":"27in 4K Gaming Monitor","quantity":1,"price":389.99,"orderdate":"2019-05-06T11:00:00.000-05:00","storeaddress":"890 9th St, New York City, NY 10001","city":" New York City","state":"NY"}
{"orderid":198915,"product":"USB-C Charging Cable","quantity":1,"price":11.95,"orderdate":"2019-05-09T15:39:00.000-05:00","storeaddress":"207 Willow St, Los Angeles, CA 90001","city":" Los Angeles","state":"CA"}
{"orderid":198988,"product":"USB-C Charging Cable","quantity":1,"price":11.95,"orderdate":"2019-05-15T17:45:00.000-05:00","storeaddress":"148 Lincoln St, Atlanta, GA 30301","city":" Atlanta","state":"GA"}
{"orderid":199052,"product":"AAA Batteries (4-pack)","quantity":1,"price":2.99,"orderdate":"2019-05-11T06:36:00.000-05:00","storeaddress":"703 Maple St, Portland, OR 97035","city":" Portland","state":"OR"}
{"orderid":199111,"product":"Lightning Charging Cable","quantity":1,"price":14.95,"orderdate":"2019-05-17T15:10:00.000-05:00","storeaddress":"642 North St, San Francisco, CA 94016","city":" San Francisco","state":"CA"}
{"orderid":199363,"product":"Lightning Charging Cable","quantity":1,"price":14.95,"orderdate":"2019-05-05T18:45:00.000-05:00","storeaddress":"239 8th St, Los Angeles, CA 90001","city":" Los Angeles","state":"CA"}
{"orderid":199444,"product":"AA Batteries (4-pack)","quantity":1,"price":3.84,"orderdate":"2019-05-28T12:38:00.000-05:00","storeaddress":"218 North St, Portland, OR 97035","city":" Portland","state":"OR"}
{"orderid":199500,"product":"Wired Headphones","quantity":2,"price":11.99,"orderdate":"2019-05-19T20:44:00.000-05:00","storeaddress":"613 Elm St, San Francisco, CA 94016","city":" San Francisco","state":"CA"}
{"orderid":200234,"product":"Bose SoundSport Headphones","quantity":1,"price":99.99,"orderdate":"2019-05-14T02:08:00.000-05:00","storeaddress":"904 4th St, Dallas, TX 75001","city":" Dallas","state":"TX"}
{"orderid":200266,"product":"AA Batteries (4-pack)","quantity":2,"price":3.84,"orderdate":"2019-05-31T10:46:00.000-05:00","storeaddress":"208 North St, New York City, NY 10001","city":" New York City","state":"NY"}
{"orderid":200298,"product":"27in FHD Monitor","quantity":1,"price":149.99,"orderdate":"2019-05-03T00:44:00.000-05:00","storeaddress":"746 River St, San Francisco, CA 94016","city":" San Francisco","state":"CA"}
{"orderid":200339,"product":"USB-C Charging Cable","quantity":1,"price":11.95,"orderdate":"2019-05-24T18:27:00.000-05:00","storeaddress":"691 Meadow St, Los Angeles, CA 90001","city":" Los Angeles","state":"CA"}
{"orderid":200386,"product":"AA Batteries (4-pack)","quantity":1,"price":3.84,"orderdate":"2019-05-24T21:49:00.000-05:00","storeaddress":"67 Hickory St, Boston, MA 02215","city":" Boston","state":"MA"}
{"orderid":200507,"product":"USB-C Charging Cable","quantity":1,"price":11.95,"orderdate":"2019-05-10T08:45:00.000-05:00","storeaddress":"376 11th St, Dallas, TX 75001","city":" Dallas","state":"TX"}
{"orderid":200697,"product":"Google Phone","quantity":1,"price":600.0,"orderdate":"2019-05-05T22:54:00.000-05:00","storeaddress":"989 Meadow St, Los Angeles, CA 90001","city":" Los Angeles","state":"CA"}
{"orderid":200741,"product":"Bose SoundSport Headphones","quantity":1,"price":99.99,"orderdate":"2019-05-18T11:01:00.000-05:00","storeaddress":"917 Ridge St, San Francisco, CA 94016","city":" San Francisco","state":"CA"}
{"orderid":200748,"product":"Bose SoundSport Headphones","quantity":1,"price":99.99,"orderdate":"2019-05-13T17:37:00.000-05:00","storeaddress":"806 7th St, Los Angeles, CA 90001","city":" Los Angeles","state":"CA"}
{"orderid":200820,"product":"Wired Headphones","quantity":1,"price":11.99,"orderdate":"2019-05-24T13:16:00.000-05:00","storeaddress":"635 Hill St, Atlanta, GA 30301","city":" Atlanta","state":"GA"}
{"orderid":200908,"product":"Apple Airpods Headphones","quantity":1,"price":150.0,"orderdate":"2019-05-02T11:55:00.000-05:00","storeaddress":"517 Dogwood St, Los Angeles, CA 90001","city":" Los Angeles","state":"CA"}
{"orderid":201027,"product":"Bose SoundSport Headphones","quantity":1,"price":99.99,"orderdate":"2019-05-04T09:16:00.000-05:00","storeaddress":"670 North St, Boston, MA 02215","city":" Boston","state":"MA"}
{"orderid":201126,"product":"AA Batteries (4-pack)","quantity":1,"price":3.84,"orderdate":"2019-05-22T23:02:00.000-05:00","storeaddress":"840 Church St, Dallas, TX 75001","city":" Dallas","state":"TX"}
{"orderid":201140,"product":"AAA Batteries (4-pack)","quantity":2,"price":2.99,"orderdate":"2019-05-08T01:22:00.000-05:00","storeaddress":"997 14th St, Portland, OR 97035","city":" Portland","state":"OR"}
{"orderid":201250,"product":"AA Batteries (4-pack)","quantity":2,"price":3.84,"orderdate":"2019-05-01T08:58:00.000-05:00","storeaddress":"662 South St, Atlanta, GA 30301","city":" Atlanta","state":"GA"}
{"orderid":201494,"product":"Wired Headphones","quantity":1,"price":11.99,"orderdate":"2019-05-25T14:08:00.000-05:00","storeaddress":"568 Pine St, San Francisco, CA 94016","city":" San Francisco","state":"CA"}
{"orderid":201565,"product":"Apple Airpods Headphones","quantity":1,"price":150.0,"orderdate":"2019-05-20T15:57:00.000-05:00","storeaddress":"621 South St, Dallas, TX 75001","city":" Dallas","state":"TX"}
{"orderid":201810,"product":"Wired Headphones","quantity":1,"price":11.99,"orderdate":"2019-05-09T17:33:00.000-05:00","storeaddress":"273 Lake St, San Francisco, CA 94016","city":" San Francisco","state":"CA"}
{"orderid":201896,"product":"34in Ultrawide Monitor","quantity":1,"price":379.99,"orderdate":"2019-05-30T20:40:00.000-05:00","storeaddress":"819 11th St, San Francisco, CA 94016","city":" San Francisco","state":"CA"}
{"orderid":202145,"product":"USB-C Charging Cable","quantity":1,"price":11.95,"orderdate":"2019-05-22T19:53:00.000-05:00","storeaddress":"938 Chestnut St, Los Angeles, CA 90001","city":" Los Angeles","state":"CA"}
{"orderid":202273,"product":"Flatscreen TV","quantity":1,"price":300.0,"orderdate":"2019-05-30T19:22:00.000-05:00","storeaddress":"200 Lake St, Seattle, WA 98101","city":" Seattle","state":"WA"}
{"orderid":202481,"product":"iPhone","quantity":1,"price":700.0,"orderdate":"2019-05-10T14:42:00.000-05:00","storeaddress":"479 Jackson St, Seattle, WA 98101","city":" Seattle","state":"WA"}
{"orderid":202526,"product":"Lightning Charging Cable","quantity":1,"price":14.95,"orderdate":"2019-05-05T11:51:00.000-05:00","storeaddress":"183 7th St, Atlanta, GA 30301","city":" Atlanta","state":"GA"}
{"orderid":203199,"product":"USB-C Charging Cable","quantity":1,"price":11.95,"orderdate":"2019-05-05T13:15:00.000-05:00","storeaddress":"209 North St, Boston, MA 02215","city":" Boston","state":"MA"}
{"orderid":203337,"product":"ThinkPad Laptop","quantity":1,"price":999.99,"orderdate":"2019-05-14T01:32:00.000-05:00","storeaddress":"874 12th St, Los Angeles, CA 90001","city":" Los Angeles","state":"CA"}
{"orderid":203341,"product":"AAA Batteries (4-pack)","quantity":2,"price":2.99,"orderdate":"2019-05-02T16:00:00.000-05:00","storeaddress":"348 10th St, Austin, TX 73301","city":" Austin","state":"TX"}
{"orderid":203402,"product":"iPhone","quantity":1,"price":700.0,"orderdate":"2019-05-09T14:38:00.000-05:00","storeaddress":"646 1st St, Los Angeles, CA 90001","city":" Los Angeles","state":"CA"}
{"orderid":203792,"product":"Apple Airpods Headphones","quantity":1,"price":150.0,"orderdate":"2019-05-01T20:27:00.000-05:00","storeaddress":"596 Lake St, San Francisco, CA 94016","city":" San Francisco","state":"CA"}
{"orderid":204098,"product":"Wired Headphones","quantity":1,"price":11.99,"orderdate":"2019-05-25T20:06:00.000-05:00","storeaddress":"705 Chestnut St, San Francisco, CA 94016","city":" San Francisco","state":"CA"}
{"orderid":204137,"product":"27in 4K Gaming Monitor","quantity":1,"price":389.99,"orderdate":"2019-05-08T12:27:00.000-05:00","storeaddress":"820 Jackson St, New York City, NY 10001","city":" New York City","state":"NY"}
{"orderid":204269,"product":"AA Batteries (4-pack)","quantity":1,"price":3.84,"orderdate":"2019-05-04T11:42:00.000-05:00","storeaddress":"439 5th St, Boston, MA 02215","city":" Boston","state":"MA"}
{"orderid":204399,"product":"Lightning Charging Cable","quantity":2,"price":14.95,"orderdate":"2019-05-23T22:44:00.000-05:00","storeaddress":"435 Chestnut St, Atlanta, GA 30301","city":" Atlanta","state":"GA"}
{"orderid":204523,"product":"USB-C Charging Cable","quantity":1,"price":11.95,"orderdate":"2019-05-01T11:26:00.000-05:00","storeaddress":"177 12th St, Seattle, WA 98101","city":" Seattle","state":"WA"}
{"orderid":204529,"product":"USB-C Charging Cable","quantity":1,"price":11.95,"orderdate":"2019-05-03T15:54:00.000-05:00","storeaddress":"201 Maple St, San Francisco, CA 94016","city":" San Francisco","state":"CA"}
{"orderid":204660,"product":"27in FHD Monitor","quantity":1,"price":149.99,"orderdate":"2019-05-21T22:28:00.000-05:00","storeaddress":"313 Church St, New York City, NY 10001","city":" New York City","state":"NY"}
{"orderid":204679,"product":"Bose SoundSport Headphones","quantity":1,"price":99.99,"orderdate":"2019-05-15T08:53:00.000-05:00","storeaddress":"527 Lincoln St, San Francisco, CA 94016","city":" San Francisco","state":"CA"}
{"orderid":204816,"product":"Flatscreen TV","quantity":1,"price":300.0,"orderdate":"2019-05-09T19:46:00.000-05:00","storeaddress":"16 Lake St, Los Angeles, CA 90001","city":" Los Angeles","state":"CA"}
{"orderid":205496,"product":"USB-C Charging Cable","quantity":1,"price":11.95,"orderdate":"2019-05-16T21:21:00.000-05:00","storeaddress":"489 1st St, San Francisco, CA 94016","city":" San Francisco","state":"CA"}
{"orderid":205500,"product":"AAA Batteries (4-pack)","quantity":2,"price":2.99,"orderdate":"2019-05-03T15:23:00.000-05:00","storeaddress":"916 Johnson St, Portland, OR 97035","city":" Portland","state":"OR"}
{"orderid":205630,"product":"ThinkPad Laptop","quantity":1,"price":999.99,"orderdate":"2019-05-14T22:54:00.000-05:00","storeaddress":"332 North St, Atlanta, GA 30301","city":" Atlanta","state":"GA"}
{"orderid":205911,"product":"20in Monitor","quantity":1,"price":109.99,"orderdate":"2019-05-29T17:10:00.000-05:00","storeaddress":"189 Jefferson St, New York City, NY 10001","city":" New York City","state":"NY"}
{"orderid":205913,"product":"Lightning Charging Cable","quantity":1,"price":14.95,"orderdate":"2019-05-17T20:25:00.000-05:00","storeaddress":"939 4th St, Austin, TX 73301","city":" Austin","state":"TX"}
{"orderid":206538,"product":"AAA Batteries (4-pack)","quantity":1,"price":2.99,"orderdate":"2019-05-26T12:41:00.000-05:00","storeaddress":"156 Highland St, San Francisco, CA 94016","city":" San Francisco","state":"CA"}
{"orderid":206746,"product":"Macbook Pro Laptop","quantity":1,"price":1700.0,"orderdate":"2019-05-02T17:08:00.000-05:00","storeaddress":"616 Cherry St, Dallas, TX 75001","city":" Dallas","state":"TX"}
{"orderid":206838,"product":"USB-C Charging Cable","quantity":1,"price":11.95,"orderdate":"2019-05-01T13:18:00.000-05:00","storeaddress":"557 Church St, Dallas, TX 75001","city":" Dallas","state":"TX"}
{"orderid":206970,"product":"Wired Headphones","quantity":1,"price":11.99,"orderdate":"2019-05-26T12:04:00.000-05:00","storeaddress":"729 2nd St, New York City, NY 10001","city":" New York City","state":"NY"}
{"orderid":206997,"product":"USB-C Charging Cable","quantity":1,"price":11.95,"orderdate":"2019-05-20T16:24:00.000-05:00","storeaddress":"661 Jackson St, Seattle, WA 98101","city":" Seattle","state":"WA"}
{"orderid":207030,"product":"27in FHD Monitor","quantity":1,"price":149.99,"orderdate":"2019-05-29T17:05:00.000-05:00","storeaddress":"608 Spruce St, Seattle, WA 98101","city":" Seattle","state":"WA"}
{"orderid":207173,"product":"AA Batteries (4-pack)","quantity":1,"price":3.84,"orderdate":"2019-05-04T13:48:00.000-05:00","storeaddress":"984 2nd St, Austin, TX 73301","city":" Austin","state":"TX"}
{"orderid":207260,"product":"34in Ultrawide Monitor","quantity":1,"price":379.99,"orderdate":"2019-05-14T22:10:00.000-05:00","storeaddress":"238 Adams St, Boston, MA 02215","city":" Boston","state":"MA"}
{"orderid":207325,"product":"Wired Headphones","quantity":2,"price":11.99,"orderdate":"2019-05-22T15:26:00.000-05:00","storeaddress":"369 Pine St, Portland, ME 04101","city":" Portland","state":"ME"}
{"orderid":207328,"product":"27in FHD Monitor","quantity":1,"price":149.99,"orderdate":"2019-05-11T21:55:00.000-05:00","storeaddress":"806 South St, San Francisco, CA 94016","city":" San Francisco","state":"CA"}
{"orderid":207331,"product":"AAA Batteries (4-pack)","quantity":1,"price":2.99,"orderdate":"2019-05-09T20:00:00.000-05:00","storeaddress":"649 14th St, Boston, MA 02215","city":" Boston","state":"MA"}
{"orderid":207735,"product":"LG Dryer","quantity":1,"price":600.0,"orderdate":"2019-05-26T20:26:00.000-05:00","storeaddress":"901 10th St, San Francisco, CA 94016","city":" San Francisco","state":"CA"}
{"orderid":207858,"product":"27in FHD Monitor","quantity":1,"price":149.99,"orderdate":"2019-05-30T20:53:00.000-05:00","storeaddress":"323 Lake St, Boston, MA 02215","city":" Boston","state":"MA"}
{"orderid":207880,"product":"AAA Batteries (4-pack)","quantity":3,"price":2.99,"orderdate":"2019-05-13T20:48:00.000-05:00","storeaddress":"718 Meadow St, New York City, NY 10001","city":" New York City","state":"NY"}
{"orderid":208370,"product":"Macbook Pro Laptop","quantity":1,"price":1700.0,"orderdate":"2019-05-06T11:19:00.000-05:00","storeaddress":"480 11th St, Boston, MA 02215","city":" Boston","state":"MA"}
{"orderid":209485,"product":"AA Batteries (4-pack)","quantity":1,"price":3.84,"orderdate":"2019-05-07T15:02:00.000-05:00","storeaddress":"44 River St, Boston, MA 02215","city":" Boston","state":"MA"}
{"orderid":209533,"product":"AAA Batteries (4-pack)","quantity":2,"price":2.99,"orderdate":"2019-05-14T12:38:00.000-05:00","storeaddress":"838 Pine St, Boston, MA 02215","city":" Boston","state":"MA"}
{"orderid":209553,"product":"AA Batteries (4-pack)","quantity":1,"price":3.84,"orderdate":"2019-05-17T21:06:00.000-05:00","storeaddress":"45 Church St, Seattle, WA 98101","city":" Seattle","state":"WA"}
{"orderid":209762,"product":"34in Ultrawide Monitor","quantity":1,"price":379.99,"orderdate":"2019-05-27T14:06:00.000-05:00","storeaddress":"940 Lakeview St, Boston, MA 02215","city":" Boston","state":"MA"}
