{"orderid":225541,"product":"27in 4K Gaming Monitor","quantity":1,"price":389.99,"orderdate":"2019-08-01T01:15:00.000-05:00","storeaddress":"480 Spruce St, Los Angeles, CA 90001","city":" Los Angeles","state":"CA"}
{"orderid":236751,"product":"27in 4K Gaming Monitor","quantity":1,"price":389.99,"orderdate":"2019-08-03T09:18:00.000-05:00","storeaddress":"534 Washington St, Portland, ME 04101","city":" Portland","state":"ME"}
{"orderid":237235,"product":"Apple Airpods Headphones","quantity":1,"price":150.0,"orderdate":"2019-08-12T21:16:00.000-05:00","storeaddress":"529 Chestnut St, San Francisco, CA 94016","city":" San Francisco","state":"CA"}
{"orderid":237361,"product":"USB-C Charging Cable","quantity":1,"price":11.95,"orderdate":"2019-08-27T15:56:00.000-05:00","storeaddress":"352 Sunset St, Portland, OR 97035","city":" Portland","state":"OR"}
{"orderid":237369,"product":"USB-C Charging Cable","quantity":1,"price":11.95,"orderdate":"2019-08-28T11:39:00.000-05:00","storeaddress":"104 Center St, Dallas, TX 75001","city":" Dallas","state":"TX"}
{"orderid":237719,"product":"Bose SoundSport Headphones","quantity":1,"price":99.99,"orderdate":"2019-08-30T20:17:00.000-05:00","storeaddress":"256 8th St, New York City, NY 10001","city":" New York City","state":"NY"}
{"orderid":237767,"product":"USB-C Charging Cable","quantity":1,"price":11.95,"orderdate":"2019-08-07T19:05:00.000-05:00","storeaddress":"359 Dogwood St, Austin, TX 73301","city":" Austin","state":"TX"}
{"orderid":238177,"product":"Wired Headphones","quantity":1,"price":11.99,"orderdate":"2019-08-07T14:55:00.000-05:00","storeaddress":"638 Dogwood St, Boston, MA 02215","city":" Boston","state":"MA"}
{"orderid":238241,"product":"LG Washing Machine","quantity":1,"price":600.0,"orderdate":"2019-08-04T12:15:00.000-05:00","storeaddress":"865 Chestnut St, New York City, NY 10001","city":" New York City","state":"NY"}
{"orderid":238387,"product":"AA Batteries (4-pack)","quantity":1,"price":3.84,"orderdate":"2019-08-24T13:25:00.000-05:00","storeaddress":"229 6th St, Portland, OR 97035","city":" Portland","state":"OR"}
{"orderid":238420,"product":"USB-C Charging Cable","quantity":1,"price":11.95,"orderdate":"2019-08-14T18:54:00.000-05:00","storeaddress":"284 Hickory St, Portland, OR 97035","city":" Portland","state":"OR"}
{"orderid":238543,"product":"Bose SoundSport Headphones","quantity":1,"price":99.99,"orderdate":"2019-08-03T00:37:00.000-05:00","storeaddress":"178 Lincoln St, Portland, OR 97035","city":" Portland","state":"OR"}
{"orderid":238789,"product":"AA Batteries (4-pack)","quantity":3,"price":3.84,"orderdate":"2019-08-25T14:59:00.000-05:00","storeaddress":"991 Cedar St, Atlanta, GA 30301","city":" Atlanta","state":"GA"}
{"orderid":238958,"product":"34in Ultrawide Monitor","quantity":1,"price":379.99,"orderdate":"2019-08-05T21:53:00.000-05:00","storeaddress":"176 Highland St, San Francisco, CA 94016","city":" San Francisco","state":"CA"}
{"orderid":238995,"product":"Apple Airpods Headphones","quantity":1,"price":150.0,"orderdate":"2019-08-07T20:50:00.000-05:00","storeaddress":"348 South St, Atlanta, GA 30301","city":" Atlanta","state":"GA"}
{"orderid":239010,"product":"27in FHD Monitor","quantity":1,"price":149.99,"orderdate":"2019-08-21T20:00:00.000-05:00","storeaddress":"704 West St, Dallas, TX 75001","city":" Dallas","state":"TX"}
{"orderid":239321,"product":"USB-C Charging Cable","quantity":1,"price":11.95,"orderdate":"2019-08-20T16:41:00.000-05:00","storeaddress":"583 Maple St, Boston, MA 02215","city":" Boston","state":"MA"}
{"orderid":239868,"product":"34in Ultrawide Monitor","quantity":1,"price":379.99,"orderdate":"2019-08-05T18:05:00.000-05:00","storeaddress":"83 West St, San Francisco, CA 94016","city":" San Francisco","state":"CA"}
{"orderid":239971,"product":"Wired Headphones","quantity":1,"price":11.99,"orderdate":"2019-08-27T15:13:00.000-05:00","storeaddress":"140 Washington St, Atlanta, GA 30301","city":" Atlanta","state":"GA"}
{"orderid":240094,"product":"Wired Headphones","quantity":2,"price":11.99,"orderdate":"2019-08-01T10:04:00.000-05:00","storeaddress":"149 Johnson St, New York City, NY 10001","city":" New York City","state":"NY"}
{"orderid":240270,"product":"Apple Airpods Headphones","quantity":1,"price":150.0,"orderdate":"2019-08-09T21:53:00.000-05:00","storeaddress":"960 Adams St, Los Angeles, CA 90001","city":" Los Angeles","state":"CA"}
{"orderid":240381,"product":"27in 4K Gaming Monitor","quantity":1,"price":389.99,"orderdate":"2019-08-09T18:05:00.000-05:00","storeaddress":"971 Madison St, Dallas, TX 75001","city":" Dallas","state":"TX"}
{"orderid":240545,"product":"Bose SoundSport Headphones","quantity":1,"price":99.99,"orderdate":"2019-08-06T16:15:00.000-05:00","storeaddress":"229 West St, Los Angeles, CA 90001","city":" Los Angeles","state":"CA"}
{"orderid":240634,"product":"Apple Airpods Headphones","quantity":1,"price":150.0,"orderdate":"2019-08-12T17:01:00.000-05:00","storeaddress":"252 13th St, Los Angeles, CA 90001","city":" Los Angeles","state":"CA"}
{"orderid":240900,"product":"USB-C Charging Cable","quantity":1,"price":11.95,"orderdate":"2019-08-24T12:17:00.000-05:00","storeaddress":"947 Washington St, San Francisco, CA 94016","city":" San Francisco","state":"CA"}
{"orderid":241092,"product":"AAA Batteries (4-pack)","quantity":1,"price":2.99,"orderdate":"2019-08-03T20:15:00.000-05:00","storeaddress":"455 Elm St, Los Angeles, CA 90001","city":" Los Angeles","state":"CA"}
{"orderid":241368,"product":"Lightning Charging Cable","quantity":1,"price":14.95,"orderdate":"2019-08-27T20:53:00.000-05:00","storeaddress":"745 Walnut St, San Francisco, CA 94016","city":" San Francisco","state":"CA"}
{"orderid":241392,"product":"Flatscreen TV","quantity":1,"price":300.0,"orderdate":"2019-08-15T21:02:00.000-05:00","storeaddress":"227 Forest St, San Francisco, CA 94016","city":" San Francisco","state":"CA"}
{"orderid":241489,"product":"Lightning Charging Cable","quantity":1,"price":14.95,"orderdate":"2019-08-10T20:49:00.000-05:00","storeaddress":"187 Ridge St, Los Angeles, CA 90001","city":" Los Angeles","state":"CA"}
{"orderid":241809,"product":"Wired Headphones","quantity":1,"price":11.99,"orderdate":"2019-08-11T12:32:00.000-05:00","storeaddress":"226 Elm St, San Francisco, CA 94016","city":" San Francisco","state":"CA"}
{"orderid":241878,"product":"Wired Headphones","quantity":1,"price":11.99,"orderdate":"2019-08-21T12:17:00.000-05:00","storeaddress":"643 Madison St, San Francisco, CA 94016","city":" San Francisco","state":"CA"}
{"orderid":241971,"product":"USB-C Charging Cable","quantity":1,"price":11.95,"orderdate":"2019-08-18T11:46:00.000-05:00","storeaddress":"738 8th St, Seattle, WA 98101","city":" Seattle","state":"WA"}
{"orderid":242744,"product":"iPhone","quantity":1,"price":700.0,"orderdate":"2019-08-14T01:02:00.000-05:00","storeaddress":"618 South St, Dallas, TX 75001","city":" Dallas","state":"TX"}
{"orderid":242898,"product":"Wired Headphones","quantity":1,"price":11.99,"orderdate":"2019-08-11T08:50:00.000-05:00","storeaddress":"619 Maple St, Atlanta, GA 30301","city":" Atlanta","state":"GA"}
{"orderid":242950,"product":"Apple Airpods Headphones","quantity":2,"price":150.0,"orderdate":"2019-08-04T14:39:00.000-05:00","storeaddress":"131 Park St, Los Angeles, CA 90001","city":" Los Angeles","state":"CA"}
{"orderid":243019,"product":"27in FHD Monitor","quantity":1,"price":149.99,"orderdate":"2019-08-04T19:55:00.000-05:00","storeaddress":"958 West St, San Francisco, CA 94016","city":" San Francisco","state":"CA"}
{"orderid":243281,"product":"Lightning Charging Cable","quantity":1,"price":14.95,"orderdate":"2019-08-27T11:20:00.000-05:00","storeaddress":"895 Washington St, San Francisco, CA 94016","city":" San Francisco","state":"CA"}
{"orderid":243511,"product":"Bose SoundSport Headphones","quantity":1,"price":99.99,"orderdate":"2019-08-22T06:30:00.000-05:00","storeaddress":"343 Pine St, Atlanta, GA 30301","city":" Atlanta","state":"GA"}
{"orderid":243578,"product":"USB-C Charging Cable","quantity":1,"price":11.95,"orderdate":"2019-08-09T08:46:00.000-05:00","storeaddress":"895 Jefferson St, San Francisco, CA 94016","city":" San Francisco","state":"CA"}
{"orderid":243595,"product":"Apple Airpods Headphones","quantity":1,"price":150.0,"orderdate":"2019-08-05T20:34:00.000-05:00","storeaddress":"943 Chestnut St, San Francisco, CA 94016","city":" San Francisco","state":"CA"}
{"orderid":243599,"product":"AAA Batteries (4-pack)","quantity":2,"price":2.99,"orderdate":"2019-08-21T14:46:00.000-05:00","storeaddress":"706 Center St, San Francisco, CA 94016","city":" San Francisco","state":"CA"}
{"orderid":243660,"product":"Lightning Charging Cable","quantity":1,"price":14.95,"orderdate":"2019-08-28T23:02:00.000-05:00","storeaddress":"250 Wilson St, Boston, MA 02215","city":" Boston","state":"MA"}
{"orderid":243735,"product":"AAA Batteries (4-pack)","quantity":4,"price":2.99,"orderdate":"2019-08-08T13:54:00.000-05:00","storeaddress":"746 Chestnut St, New York City, NY 10001","city":" New York City","state":"NY"}
{"orderid":244087,"product":"Google Phone","quantity":1,"price":600.0,"orderdate":"2019-08-29T07:18:00.000-05:00","storeaddress":"792 Forest St, Seattle, WA 98101","city":" Seattle","state":"WA"}
{"orderid":244106,"product":"27in FHD Monitor","quantity":1,"price":149.99,"orderdate":"2019-08-03T14:43:00.000-05:00","storeaddress":"176 11th St, Dallas, TX 75001","city":" Dallas","state":"TX"}
{"orderid":244210,"product":"ThinkPad Laptop","quantity":1,"price":999.99,"orderdate":"2019-08-13T18:11:00.000-05:00","storeaddress":"668 Church St, Atlanta, GA 30301","city":" Atlanta","state":"GA"}
{"orderid":244223,"product":"Bose SoundSport Headphones","quantity":1,"price":99.99,"orderdate":"2019-08-18T14:08:00.000-05:00","storeaddress":"102 Cherry St, Dallas, TX 75001","city":" Dallas","state":"TX"}
{"orderid":244539,"product":"Apple Airpods Headphones","quantity":1,"price":150.0,"orderdate":"2019-08-26T11:43:00.000-05:00","storeaddress":"188 13th St, Atlanta, GA 30301","city":" Atlanta","state":"GA"}
{"orderid":245429,"product":"AAA Batteries (4-pack)","quantity":1,"price":2.99,"orderdate":"2019-08-05T19:00:00.000-05:00","storeaddress":"998 Spruce St, Boston, MA 02215","city":" Boston","state":"MA"}
{"orderid":245552,"product":"USB-C Charging Cable","quantity":1,"price":11.95,"orderdate":"2019-08-30T14:14:00.000-05:00","storeaddress":"380 Lakeview St, Los Angeles, CA 90001","city":" Los Angeles","state":"CA"}
{"orderid":245805,"product":"AAA Batteries (4-pack)","quantity":5,"price":2.99,"orderdate":"2019-08-21T20:07:00.000-05:00","storeaddress":"618 Jackson St, Los Angeles, CA 90001","city":" Los Angeles","state":"CA"}
{"orderid":245813,"product":"ThinkPad Laptop","quantity":1,"price":999.99,"orderdate":"2019-08-28T17:59:00.000-05:00","storeaddress":"391 Cherry St, Los Angeles, CA 90001","city":" Los Angeles","state":"CA"}
{"orderid":245864,"product":"Bose SoundSport Headphones","quantity":1,"price":99.99,"orderdate":"2019-08-29T19:57:00.000-05:00","storeaddress":"678 8th St, Boston, MA 02215","city":" Boston","state":"MA"}
{"orderid":245990,"product":"Wired Headphones","quantity":1,"price":11.99,"orderdate":"2019-08-16T08:30:00.000-05:00","storeaddress":"109 Chestnut St, New York City, NY 10001","city":" New York City","state":"NY"}
{"orderid":246194,"product":"27in 4K Gaming Monitor","quantity":1,"price":389.99,"orderdate":"2019-08-17T12:29:00.000-05:00","storeaddress":"285 Lincoln St, San Francisco, CA 94016","city":" San Francisco","state":"CA"}
{"orderid":247044,"product":"AAA Batteries (4-pack)","quantity":1,"price":2.99,"orderdate":"2019-08-16T17:26:00.000-05:00","storeaddress":"21 Jackson St, Los Angeles, CA 90001","city":" Los Angeles","state":"CA"}
{"orderid":247320,"product":"USB-C Charging Cable","quantity":1,"price":11.95,"orderdate":"2019-08-17T13:22:00.000-05:00","storeaddress":"164 Pine St, New York City, NY 10001","city":" New York City","state":"NY"}
{"orderid":247681,"product":"Bose SoundSport Headphones","quantity":1,"price":99.99,"orderdate":"2019-08-06T12:01:00.000-05:00","storeaddress":"391 Johnson St, Los Angeles, CA 90001","city":" Los Angeles","state":"CA"}
{"orderid":247830,"product":"Lightning Charging Cable","quantity":1,"price":14.95,"orderdate":"2019-08-12T20:07:00.000-05:00","storeaddress":"699 Washington St, Dallas, TX 75001","city":" Dallas","state":"TX"}
{"orderid":247899,"product":"Apple Airpods Headphones","quantity":1,"price":150.0,"orderdate":"2019-08-09T16:29:00.000-05:00","storeaddress":"253 South St, Austin, TX 73301","city":" Austin","state":"TX"}
{"orderid":247913,"product":"Apple Airpods Headphones","quantity":1,"price":150.0,"orderdate":"2019-08-24T19:05:00.000-05:00","storeaddress":"842 Madison St, Boston, MA 02215","city":" Boston","state":"MA"}
{"orderid":248006,"product":"Apple Airpods Headphones","quantity":1,"price":150.0,"orderdate":"2019-08-13T13:06:00.000-05:00","storeaddress":"510 Johnson St, San Francisco, CA 94016","city":" San Francisco","state":"CA"}
