{"orderid":248235,"product":"Lightning Charging Cable","quantity":1,"price":14.95,"orderdate":"2019-09-26T20:16:00.000-05:00","storeaddress":"374 Cherry St, San Francisco, CA 94016","city":" San Francisco","state":"CA"}
{"orderid":248450,"product":"Apple Airpods Headphones","quantity":1,"price":150.0,"orderdate":"2019-09-30T11:36:00.000-05:00","storeaddress":"822 11th St, San Francisco, CA 94016","city":" San Francisco","state":"CA"}
{"orderid":248539,"product":"27in 4K Gaming Monitor","quantity":1,"price":389.99,"orderdate":"2019-09-01T14:19:00.000-05:00","storeaddress":"255 12th St, Portland, ME 04101","city":" Portland","state":"ME"}
{"orderid":248715,"product":"Wired Headphones","quantity":1,"price":11.99,"orderdate":"2019-09-02T00:11:00.000-05:00","storeaddress":"622 South St, Los Angeles, CA 90001","city":" Los Angeles","state":"CA"}
{"orderid":248727,"product":"Apple Airpods Headphones","quantity":1,"price":150.0,"orderdate":"2019-09-20T14:14:00.000-05:00","storeaddress":"583 Pine St, Portland, ME 04101","city":" Portland","state":"ME"}
{"orderid":248951,"product":"27in FHD Monitor","quantity":1,"price":149.99,"orderdate":"2019-09-02T22:57:00.000-05:00","storeaddress":"284 Lake St, Seattle, WA 98101","city":" Seattle","state":"WA"}
{"orderid":249179,"product":"Vareebadd Phone","quantity":1,"price":400.0,"orderdate":"2019-09-14T22:31:00.000-05:00","storeaddress":"400 Park St, Los Angeles, CA 90001","city":" Los Angeles","state":"CA"}
{"orderid":249407,"product":"Macbook Pro Laptop","quantity":1,"price":1700.0,"orderdate":"2019-09-28T15:21:00.000-05:00","storeaddress":"302 Elm St, San Francisco, CA 94016","city":" San Francisco","state":"CA"}
{"orderid":249460,"product":"Lightning Charging Cable","quantity":1,"price":14.95,"orderdate":"2019-09-19T18:33:00.000-05:00","storeaddress":"719 10th St, San Francisco, CA 94016","city":" San Francisco","state":"CA"}
{"orderid":250185,"product":"AAA Batteries (4-pack)","quantity":1,"price":2.99,"orderdate":"2019-09-18T00:46:00.000-05:00","storeaddress":"354 River St, New York City, NY 10001","city":" New York City","state":"NY"}
{"orderid":250801,"product":"Bose SoundSport Headphones","quantity":1,"price":99.99,"orderdate":"2019-09-04T09:07:00.000-05:00","storeaddress":"231 Elm St, Boston, MA 02215","city":" Boston","state":"MA"}
{"orderid":250937,"product":"AA Batteries (4-pack)","quantity":2,"price":3.84,"orderdate":"2019-09-28T20:09:00.000-05:00","storeaddress":"437 Hill St, Boston, MA 02215","city":" Boston","state":"MA"}
{"orderid":251030,"product":"AAA Batteries (4-pack)","quantity":1,"price":2.99,"orderdate":"2019-09-01T12:33:00.000-05:00","storeaddress":"906 Cedar St, San Francisco, CA 94016","city":" San Francisco","state":"CA"}
{"orderid":251083,"product":"AA Batteries (4-pack)","quantity":2,"price":3.84,"orderdate":"2019-09-28T15:34:00.000-05:00","storeaddress":"714 Ridge St, Seattle, WA 98101","city":" Seattle","state":"WA"}
{"orderid":251223,"product":"AAA Batteries (4-pack)","quantity":3,"price":2.99,"orderdate":"2019-09-21T09:44:00.000-05:00","storeaddress":"584 Spruce St, Dallas, TX 75001","city":" Dallas","state":"TX"}
{"orderid":251244,"product":"USB-C Charging Cable","quantity":1,"price":11.95,"orderdate":"2019-09-07T11:51:00.000-05:00","storeaddress":"973 Adams St, Seattle, WA 98101","city":" Seattle","state":"WA"}
{"orderid":251339,"product":"20in Monitor","quantity":1,"price":109.99,"orderdate":"2019-09-17T08:48:00.000-05:00","storeaddress":"620 Washington St, Los Angeles, CA 90001","city":" Los Angeles","state":"CA"}
{"orderid":251347,"product":"AA Batteries (4-pack)","quantity":1,"price":3.84,"orderdate":"2019-09-28T20:35:00.000-05:00","storeaddress":"65 Chestnut St, Atlanta, GA 30301","city":" Atlanta","state":"GA"}
{"orderid":251462,"product":"27in FHD Monitor","quantity":1,"price":149.99,"orderdate":"2019-09-18T13:10:00.000-05:00","storeaddress":"33 Forest St, Atlanta, GA 30301","city":" Atlanta","state":"GA"}
{"orderid":251631,"product":"AA Batteries (4-pack)","quantity":2,"price":3.84,"orderdate":"2019-09-30T21:46:00.000-05:00","storeaddress":"135 7th St, Austin, TX 73301","city":" Austin","state":"TX"}
{"orderid":251756,"product":"Apple Airpods Headphones","quantity":1,"price":150.0,"orderdate":"2019-09-15T21:20:00.000-05:00","storeaddress":"767 Jefferson St, Austin, TX 73301","city":" Austin","state":"TX"}
{"orderid":251759,"product":"USB-C Charging Cable","quantity":1,"price":11.95,"orderdate":"2019-09-11T20:39:00.000-05:00","storeaddress":"749 11th St, New York City, NY 10001","city":" New York City","state":"NY"}
{"orderid":252139,"product":"Wired Headphones","quantity":1,"price":11.99,"orderdate":"2019-09-17T11:39:00.000-05:00","storeaddress":"844 Hill St, San Francisco, CA 94016","city":" San Francisco","state":"CA"}
{"orderid":252142,"product":"Google Phone","quantity":1,"price":600.0,"orderdate":"2019-09-18T20:00:00.000-05:00","storeaddress":"520 Willow St, Boston, MA 02215","city":" Boston","state":"MA"}
{"orderid":252283,"product":"Lightning Charging Cable","quantity":1,"price":14.95,"orderdate":"2019-09-10T21:49:00.000-05:00","storeaddress":"421 Washington St, San Francisco, CA 94016","city":" San Francisco","state":"CA"}
{"orderid":252379,"product":"USB-C Charging Cable","quantity":1,"price":11.95,"orderdate":"2019-09-20T10:10:00.000-05:00","storeaddress":"80 Maple St, Boston, MA 02215","city":" Boston","state":"MA"}
{"orderid":252398,"product":"Vareebadd Phone","quantity":1,"price":400.0,"orderdate":"2019-09-06T14:24:00.000-05:00","storeaddress":"399 North St, San Francisco, CA 94016","city":" San Francisco","state":"CA"}
{"orderid":252509,"product":"Wired Headphones","quantity":1,"price":11.99,"orderdate":"2019-09-12T17:36:00.000-05:00","storeaddress":"77 Church St, New York City, NY 10001","city":" New York City","state":"NY"}
{"orderid":252897,"product":"iPhone","quantity":1,"price":700.0,"orderdate":"2019-09-12T23:43:00.000-05:00","storeaddress":"236 Jefferson St, New York City, NY 10001","city":" New York City","state":"NY"}
{"orderid":253532,"product":"Wired Headphones","quantity":1,"price":11.99,"orderdate":"2019-09-08T21:27:00.000-05:00","storeaddress":"390 Lake St, Atlanta, GA 30301","city":" Atlanta","state":"GA"}
{"orderid":253550,"product":"Lightning Charging Cable","quantity":1,"price":14.95,"orderdate":"2019-09-19T22:09:00.000-05:00","storeaddress":"244 Main St, New York City, NY 10001","city":" New York City","state":"NY"}
{"orderid":253603,"product":"Vareebadd Phone","quantity":1,"price":400.0,"orderdate":"2019-09-12T07:22:00.000-05:00","storeaddress":"396 6th St, San Francisco, CA 94016","city":" San Francisco","state":"CA"}
{"orderid":253828,"product":"Wired Headphones","quantity":1,"price":11.99,"orderdate":"2019-09-03T11:42:00.000-05:00","storeaddress":"974 Highland St, Los Angeles, CA 90001","city":" Los Angeles","state":"CA"}
{"orderid":253843,"product":"Bose SoundSport Headphones","quantity":1,"price":99.99,"orderdate":"2019-09-06T20:53:00.000-05:00","storeaddress":"204 Cherry St, Dallas, TX 75001","city":" Dallas","state":"TX"}
{"orderid":254191,"product":"AAA Batteries (4-pack)","quantity":2,"price":2.99,"orderdate":"2019-09-04T14:22:00.000-05:00","storeaddress":"36 Willow St, Austin, TX 73301","city":" Austin","state":"TX"}
{"orderid":254363,"product":"Apple Airpods Headphones","quantity":1,"price":150.0,"orderdate":"2019-09-12T19:06:00.000-05:00","storeaddress":"694 Madison St, Austin, TX 73301","city":" Austin","state":"TX"}
{"orderid":254387,"product":"AAA Batteries (4-pack)","quantity":1,"price":2.99,"orderdate":"2019-09-09T12:24:00.000-05:00","storeaddress":"156 1st St, New York City, NY 10001","city":" New York City","state":"NY"}
{"orderid":254470,"product":"Bose SoundSport Headphones","quantity":1,"price":99.99,"orderdate":"2019-09-07T06:32:00.000-05:00","storeaddress":"575 5th St, New York City, NY 10001","city":" New York City","state":"NY"}
{"orderid":254686,"product":"27in FHD Monitor","quantity":1,"price":149.99,"orderdate":"2019-09-19T20:36:00.000-05:00","storeaddress":"285 Elm St, New York City, NY 10001","city":" New York City","state":"NY"}
{"orderid":254694,"product":"Bose SoundSport Headphones","quantity":1,"price":99.99,"orderdate":"2019-09-26T12:50:00.000-05:00","storeaddress":"708 Jefferson St, Austin, TX 73301","city":" Austin","state":"TX"}
{"orderid":254956,"product":"Bose SoundSport Headphones","quantity":1,"price":99.99,"orderdate":"2019-09-22T23:11:00.000-05:00","storeaddress":"587 Jefferson St, Austin, TX 73301","city":" Austin","state":"TX"}
{"orderid":254985,"product":"Lightning Charging Cable","quantity":1,"price":14.95,"orderdate":"2019-09-12T10:25:00.000-05:00","storeaddress":"816 12th St, Austin, TX 73301","city":" Austin","state":"TX"}
{"orderid":255098,"product":"AA Batteries (4-pack)","quantity":1,"price":3.84,"orderdate":"2019-09-05T17:13:00.000-05:00","storeaddress":"869 Wilson St, Seattle, WA 98101","city":" Seattle","state":"WA"}
{"orderid":255454,"product":"Wired Headphones","quantity":1,"price":11.99,"orderdate":"2019-09-30T08:33:00.000-05:00","storeaddress":"215 Johnson St, Dallas, TX 75001","city":" Dallas","state":"TX"}
{"orderid":255736,"product":"AAA Batteries (4-pack)","quantity":1,"price":2.99,"orderdate":"2019-09-14T21:19:00.000-05:00","storeaddress":"634 2nd St, Los Angeles, CA 90001","city":" Los Angeles","state":"CA"}
{"orderid":255786,"product":"Apple Airpods Headphones","quantity":1,"price":150.0,"orderdate":"2019-09-27T08:14:00.000-05:00","storeaddress":"308 Spruce St, Boston, MA 02215","city":" Boston","state":"MA"}
{"orderid":256403,"product":"27in FHD Monitor","quantity":1,"price":149.99,"orderdate":"2019-09-03T02:24:00.000-05:00","storeaddress":"104 Maple St, Boston, MA 02215","city":" Boston","state":"MA"}
{"orderid":256470,"product":"Wired Headphones","quantity":1,"price":11.99,"orderdate":"2019-09-27T18:03:00.000-05:00","storeaddress":"103 Lincoln St, San Francisco, CA 94016","city":" San Francisco","state":"CA"}
{"orderid":256933,"product":"AA Batteries (4-pack)","quantity":2,"price":3.84,"orderdate":"2019-09-16T22:32:00.000-05:00","storeaddress":"869 West St, Atlanta, GA 30301","city":" Atlanta","state":"GA"}
{"orderid":257051,"product":"AA Batteries (4-pack)","quantity":1,"price":3.84,"orderdate":"2019-09-12T20:48:00.000-05:00","storeaddress":"505 Cherry St, New York City, NY 10001","city":" New York City","state":"NY"}
{"orderid":258066,"product":"Lightning Charging Cable","quantity":1,"price":14.95,"orderdate":"2019-09-27T18:39:00.000-05:00","storeaddress":"828 South St, Boston, MA 02215","city":" Boston","state":"MA"}
{"orderid":258667,"product":"AA Batteries (4-pack)","quantity":1,"price":3.84,"orderdate":"2019-09-01T13:39:00.000-05:00","storeaddress":"4 Meadow St, Dallas, TX 75001","city":" Dallas","state":"TX"}
{"orderid":258904,"product":"USB-C Charging Cable","quantity":1,"price":11.95,"orderdate":"2019-09-08T16:24:00.000-05:00","storeaddress":"628 5th St, Dallas, TX 75001","city":" Dallas","state":"TX"}
{"orderid":259203,"product":"AAA Batteries (4-pack)","quantity":1,"price":2.99,"orderdate":"2019-09-02T16:16:00.000-05:00","storeaddress":"353 North St, San Francisco, CA 94016","city":" San Francisco","state":"CA"}
